{
    "author": "Market",
    "description": "guys, i have great mod idea are u ready? its called \"in game matchmaking\" you click a button and it pairs you up with another person that speaks the same language as you one of you picks defuser one picks expert one gets the bomb the other gets an in game manual someone make this pls thanks",
    "manualUrl": "",
    "name": "In-game Matchmaking",
    "notes": "I apologize in advance if the way i structured this entry makes it seem like it isn't good.",
    "state": "notReady"
}