{
    "author": "MoMo",
    "description": "The defuser is given a play button that will play a melody. He has to sing it to his experts who then have to modify the tune and give back the correct notes in order for this module to be defused.",
    "manualUrl": "https://www.jotform.com/uploads/KeepTalking/62686042776162/352817434961578659/melodies.pdf",
    "name": "Melodies",
    "notes": "Author may be difficult to contact, please check 'Old Manual Spreadsheet' if you want better contact details.",
    "state": "ready"
}